wacky/__init__.py
wacky/basic_types/floats.py
wacky/basic_types/guid.py
wacky/basic_types/integers.py
wacky/basic_types/large_bool.py
wacky/basic_types/package_index.py
wacky/basic_types/string.py
wacky/cli.py
wacky/enums/adapter.py
wacky/enums/compression_flags.py
wacky/enums/object_flags.py
wacky/enums/package_flags.py
wacky/enums/ue4_version.py
wacky/hashing/lookup_tables.py
wacky/hashing/strings.py
wacky/load_and_dump.py
wacky/package.py
wacky/structs/localization_metadata.py
wacky/version.py
wacky-1.0.1.dist-info/entry_points.txt
wacky-1.0.1.dist-info/WHEEL
wacky-1.0.1.dist-info/METADATA
wacky-1.0.1.dist-info/RECORD
