Metadata-Version: 2.1
Name: wacky
Version: 1.0.1
Summary: Wacca DataTable files loading + dumping
Home-page: https://gitlab.com/Buggyroom/wacky
Author: Stepland
Author-email: 10530295-Buggyroom@users.noreply.gitlab.com
Requires-Python: >=3.8,<4.0
Classifier: Programming Language :: Python :: 3
Classifier: Programming Language :: Python :: 3.10
Classifier: Programming Language :: Python :: 3.8
Classifier: Programming Language :: Python :: 3.9
Requires-Dist: click (>=8.0.4,<9.0.0)
Requires-Dist: construct-typing (>=0.5.2,<0.6.0)
Requires-Dist: ruamel.yaml (>=0.17.21,<0.18.0)
Project-URL: Repository, https://gitlab.com/Buggyroom/wacky
